{
    "troopMemberNumSeq": 286,
    "list": [
        {
            "uin": 173704023,
            "nick": "天堂麻弥",
            "permission": "MEMBER",
            "remark": "天堂麻弥",
            "nameCard": "",
            "specialTitle": "",
            "muteTimestamp": 0,
            "anonymousId": null,
            "joinTimestamp": 1616489122,
            "lastSpeakTimestamp": 1677748321,
            "isOfficialBot": false,
            "rank": 1,
            "point": 0,
            "honors": [
            ],
            "temperature": 4
        },
        {
            "uin": 275019811,
            "nick": "Will-Tex",
            "permission": "MEMBER",
            "remark": "Will-Tex",
            "nameCard": "",
            "specialTitle": "",
            "muteTimestamp": 0,
            "anonymousId": null,
            "joinTimestamp": 1616048812,
            "lastSpeakTimestamp": 1678807622,
            "isOfficialBot": false,
            "rank": 1,
            "point": 0,
            "honors": [
            ],
            "temperature": 26
        },
        {
            "uin": 276847287,
            "nick": "World Rejecter",
            "permission": "MEMBER",
            "remark": "World Rejecter",
            "nameCard": "",
            "specialTitle": "",
            "muteTimestamp": 0,
            "anonymousId": null,
            "joinTimestamp": 1616049478,
            "lastSpeakTimestamp": 1692008715,
            "isOfficialBot": false,
            "rank": 3,
            "point": 490,
            "honors": [
            ],
            "temperature": 74
        },
        {
            "uin": 279578836,
            "nick": "tower",
            "permission": "MEMBER",
            "remark": "tower",
            "nameCard": "",
            "specialTitle": "",
            "muteTimestamp": 0,
            "anonymousId": null,
            "joinTimestamp": 1652849904,
            "lastSpeakTimestamp": 1693153367,
            "isOfficialBot": false,
            "rank": 1,
            "point": 0,
            "honors": [
            ],
            "temperature": 71
        },
        {
            "uin": 313282530,
            "nick": "..何去何从..匆匆",
            "permission": "MEMBER",
            "remark": "..何去何从..匆匆",
            "nameCard": "",
            "specialTitle": "",
            "muteTimestamp": 0,
            "anonymousId": null,
            "joinTimestamp": 1619848203,
            "lastSpeakTimestamp": 1619848203,
            "isOfficialBot": false,
            "rank": 1,
            "point": 0,
            "honors": [
            ],
            "temperature": 0
        },
        {
            "uin": 415723763,
            "nick": "Cello",
            "permission": "ADMINISTRATOR",
            "remark": "",
            "nameCard": "141cm",
            "specialTitle": "",
            "muteTimestamp": 0,
            "anonymousId": null,
            "joinTimestamp": 1616048270,
            "lastSpeakTimestamp": 1693494677,
            "isOfficialBot": false,
            "rank": 3,
            "point": 210,
            "honors": [
            ],
            "temperature": 100
        },
        {
            "uin": 542912267,
            "nick": "星の夜",
            "permission": "MEMBER",
            "remark": "星の夜",
            "nameCard": "",
            "specialTitle": "",
            "muteTimestamp": 0,
            "anonymousId": null,
            "joinTimestamp": 1616048151,
            "lastSpeakTimestamp": 1691257438,
            "isOfficialBot": false,
            "rank": 1,
            "point": 0,
            "honors": [
            ],
            "temperature": 13
        },
        {
            "uin": 546158738,
            "nick": "飘荡",
            "permission": "MEMBER",
            "remark": "飘荡",
            "nameCard": "",
            "specialTitle": "",
            "muteTimestamp": 0,
            "anonymousId": null,
            "joinTimestamp": 1616138080,
            "lastSpeakTimestamp": 1649947342,
            "isOfficialBot": false,
            "rank": 2,
            "point": 1,
            "honors": [
            ],
            "temperature": 13
        },
        {
            "uin": 598012552,
            "nick": "⠀",
            "permission": "MEMBER",
            "remark": "⠀",
            "nameCard": "",
            "specialTitle": "",
            "muteTimestamp": 0,
            "anonymousId": null,
            "joinTimestamp": 1676949605,
            "lastSpeakTimestamp": 1693492647,
            "isOfficialBot": false,
            "rank": 1,
            "point": 0,
            "honors": [
            ],
            "temperature": 13
        },
        {
            "uin": 676556236,
            "nick": "Minutes to Midnight",
            "permission": "MEMBER",
            "remark": "",
            "nameCard": "白马？定叫他有来无回",
            "specialTitle": "",
            "muteTimestamp": 0,
            "anonymousId": null,
            "joinTimestamp": 1659702568,
            "lastSpeakTimestamp": 1693374047,
            "isOfficialBot": false,
            "rank": 1,
            "point": 0,
            "honors": [
            ],
            "temperature": 95
        },
        {
            "uin": 736183934,
            "nick": "无芯灯",
            "permission": "MEMBER",
            "remark": "无芯灯",
            "nameCard": "",
            "specialTitle": "",
            "muteTimestamp": 0,
            "anonymousId": null,
            "joinTimestamp": 1621837027,
            "lastSpeakTimestamp": 1693408015,
            "isOfficialBot": false,
            "rank": 2,
            "point": 115,
            "honors": [
            ],
            "temperature": 70
        },
        {
            "uin": 749897625,
            "nick": "Tatum_",
            "permission": "MEMBER",
            "remark": "",
            "nameCard": "不会养马  8力进王981064999",
            "specialTitle": "",
            "muteTimestamp": 0,
            "anonymousId": null,
            "joinTimestamp": 1618978890,
            "lastSpeakTimestamp": 1656304005,
            "isOfficialBot": false,
            "rank": 2,
            "point": 37,
            "honors": [
            ],
            "temperature": 24
        },
        {
            "uin": 754761009,
            "nick": "Ryan1250@倒车苦手",
            "permission": "MEMBER",
            "remark": "",
            "nameCard": "出来混 要的是诗力 扣的是背景 你哪个道上的",
            "specialTitle": "",
            "muteTimestamp": 0,
            "anonymousId": null,
            "joinTimestamp": 1622354798,
            "lastSpeakTimestamp": 1693153319,
            "isOfficialBot": false,
            "rank": 2,
            "point": 97,
            "honors": [
            ],
            "temperature": 44
        },
        {
            "uin": 775231770,
            "nick": "-雪月風花。",
            "permission": "ADMINISTRATOR",
            "remark": "",
            "nameCard": "6速3力4中4ura东海帝王 满破曼城茶座 226504878",
            "specialTitle": "",
            "muteTimestamp": 0,
            "anonymousId": null,
            "joinTimestamp": 1616048620,
            "lastSpeakTimestamp": 1693471131,
            "isOfficialBot": false,
            "rank": 4,
            "point": 645,
            "honors": [
                2,
                1
            ],
            "temperature": 100
        },
        {
            "uin": 920759985,
            "nick": "LaplaZe",
            "permission": "MEMBER",
            "remark": "LaplaZe",
            "nameCard": "",
            "specialTitle": "",
            "muteTimestamp": 0,
            "anonymousId": null,
            "joinTimestamp": 1675869603,
            "lastSpeakTimestamp": 1693479928,
            "isOfficialBot": false,
            "rank": 1,
            "point": 0,
            "honors": [
            ],
            "temperature": 43
        },
        {
            "uin": 940026369,
            "nick": "Onakoro",
            "permission": "MEMBER",
            "remark": "Onakoro",
            "nameCard": "",
            "specialTitle": "",
            "muteTimestamp": 0,
            "anonymousId": null,
            "joinTimestamp": 1616144184,
            "lastSpeakTimestamp": 1629730150,
            "isOfficialBot": false,
            "rank": 3,
            "point": 294,
            "honors": [
            ],
            "temperature": 40
        },
        {
            "uin": 1030939761,
            "nick": "Nacl83333736",
            "permission": "MEMBER",
            "remark": "",
            "nameCard": "电申论出题壬的撚",
            "specialTitle": "",
            "muteTimestamp": 0,
            "anonymousId": null,
            "joinTimestamp": 1616048503,
            "lastSpeakTimestamp": 1693149271,
            "isOfficialBot": false,
            "rank": 2,
            "point": 8,
            "honors": [
            ],
            "temperature": 100
        },
        {
            "uin": 1049392583,
            "nick": "A橘長",
            "permission": "MEMBER",
            "remark": "A橘長",
            "nameCard": "",
            "specialTitle": "",
            "muteTimestamp": 0,
            "anonymousId": null,
            "joinTimestamp": 1674300937,
            "lastSpeakTimestamp": 1693324197,
            "isOfficialBot": false,
            "rank": 1,
            "point": 0,
            "honors": [
            ],
            "temperature": 26
        },
        {
            "uin": 1146005341,
            "nick": "axindwk",
            "permission": "MEMBER",
            "remark": "axindwk",
            "nameCard": "",
            "specialTitle": "",
            "muteTimestamp": 0,
            "anonymousId": null,
            "joinTimestamp": 1676949689,
            "lastSpeakTimestamp": 1684221799,
            "isOfficialBot": false,
            "rank": 1,
            "point": 0,
            "honors": [
            ],
            "temperature": 2
        },
        {
            "uin": 1259713494,
            "nick": "G11Zzz",
            "permission": "MEMBER",
            "remark": "G11Zzz",
            "nameCard": "",
            "specialTitle": "",
            "muteTimestamp": 0,
            "anonymousId": null,
            "joinTimestamp": 1677143031,
            "lastSpeakTimestamp": 1693226535,
            "isOfficialBot": false,
            "rank": 1,
            "point": 0,
            "honors": [
            ],
            "temperature": 50
        },
        {
            "uin": 1638785879,
            "nick": "我的QQ",
            "permission": "MEMBER",
            "remark": "",
            "nameCard": "哼哼",
            "specialTitle": "",
            "muteTimestamp": 0,
            "anonymousId": null,
            "joinTimestamp": 1676949715,
            "lastSpeakTimestamp": 1677994817,
            "isOfficialBot": false,
            "rank": 1,
            "point": 0,
            "honors": [
            ],
            "temperature": 3
        },
        {
            "uin": 1874399620,
            "nick": "十早月",
            "permission": "ADMINISTRATOR",
            "remark": "",
            "nameCard": "十早月",
            "specialTitle": "",
            "muteTimestamp": 0,
            "anonymousId": null,
            "joinTimestamp": 1616049289,
            "lastSpeakTimestamp": 1693444269,
            "isOfficialBot": false,
            "rank": 4,
            "point": 654,
            "honors": [
            ],
            "temperature": 100
        },
        {
            "uin": 2466701292,
            "nick": "独恋樱花",
            "permission": "OWNER",
            "remark": "",
            "nameCard": "界徐盛",
            "specialTitle": "",
            "muteTimestamp": 0,
            "anonymousId": null,
            "joinTimestamp": 1616048293,
            "lastSpeakTimestamp": 1693497148,
            "isOfficialBot": false,
            "rank": 3,
            "point": 612,
            "honors": [
                3
            ],
            "temperature": 100
        },
        {
            "uin": 2487964820,
            "nick": "Vue.js",
            "permission": "MEMBER",
            "remark": "",
            "nameCard": "不伟不吹",
            "specialTitle": "",
            "muteTimestamp": 0,
            "anonymousId": null,
            "joinTimestamp": 1676949667,
            "lastSpeakTimestamp": 1693070084,
            "isOfficialBot": false,
            "rank": 1,
            "point": 0,
            "honors": [
            ],
            "temperature": 29
        },
        {
            "uin": 2805416330,
            "nick": "幻月",
            "permission": "MEMBER",
            "remark": "幻月",
            "nameCard": "",
            "specialTitle": "",
            "muteTimestamp": 0,
            "anonymousId": null,
            "joinTimestamp": 1659676797,
            "lastSpeakTimestamp": 1693367012,
            "isOfficialBot": false,
            "rank": 1,
            "point": 0,
            "honors": [
            ],
            "temperature": 57
        },
        {
            "uin": 2925642107,
            "nick": "A Sky Full of Stars",
            "permission": "ADMINISTRATOR",
            "remark": "",
            "nameCard": "三角 9力特别周麦昆 435647190",
            "specialTitle": "",
            "muteTimestamp": 1645885512,
            "anonymousId": null,
            "joinTimestamp": 1616049232,
            "lastSpeakTimestamp": 1692007216,
            "isOfficialBot": false,
            "rank": 5,
            "point": 673,
            "honors": [
            ],
            "temperature": 100
        },
        {
            "uin": 2983455908,
            "nick": "摸鱼",
            "permission": "MEMBER",
            "remark": "摸鱼",
            "nameCard": "",
            "specialTitle": "",
            "muteTimestamp": 0,
            "anonymousId": null,
            "joinTimestamp": 1658712496,
            "lastSpeakTimestamp": 1693494840,
            "isOfficialBot": false,
            "rank": 1,
            "point": 0,
            "honors": [
            ],
            "temperature": 100
        },
        {
            "uin": 3226733245,
            "nick": "りりむ",
            "permission": "MEMBER",
            "remark": "りりむ",
            "nameCard": "",
            "specialTitle": "",
            "muteTimestamp": 0,
            "anonymousId": null,
            "joinTimestamp": 1634978188,
            "lastSpeakTimestamp": 1693459306,
            "isOfficialBot": false,
            "rank": 1,
            "point": 0,
            "honors": [
            ],
            "temperature": 64
        },
        {
            "uin": 3591283847,
            "nick": "AOS2H",
            "permission": "MEMBER",
            "remark": "吴卓衡",
            "nameCard": "",
            "specialTitle": "",
            "muteTimestamp": 0,
            "anonymousId": null,
            "joinTimestamp": 1671895173,
            "lastSpeakTimestamp": 1693471999,
            "isOfficialBot": false,
            "rank": 1,
            "point": 0,
            "honors": [
            ],
            "temperature": 84
        }
    ]
}